orm_bitrix24/entity/__init__.py
orm_bitrix24/entity/activity.py
orm_bitrix24/entity/base.py
orm_bitrix24/entity/base.pyi
orm_bitrix24/entity/company.py
orm_bitrix24/entity/contact.py
orm_bitrix24/entity/deal.py
orm_bitrix24/entity/deal.pyi
orm_bitrix24/entity/lead.py
orm_bitrix24/entity/note.py
orm_bitrix24/entity/portal.py
orm_bitrix24/entity/timeline.py
orm_bitrix24/entity/timeline.pyi
orm_bitrix24-0.1.4.dist-info/METADATA
orm_bitrix24-0.1.4.dist-info/WHEEL
orm_bitrix24-0.1.4.dist-info/top_level.txt
orm_bitrix24-0.1.4.dist-info/RECORD
