Metadata-Version: 2.4
Name: orm-bitrix24
Version: 0.1.4
Summary: ORM for Bitrix24 REST API
Project-URL: Homepage, https://github.com/darkClaw921/orm_bitrix24
Project-URL: Documentation, https://github.com/darkClaw921/orm_bitrix24
Project-URL: Repository, https://github.com/darkClaw921/orm_bitrix24.git
Project-URL: Bug Tracker, https://github.com/darkClaw921/orm_bitrix24/issues
Project-URL: Changelog, https://github.com/darkClaw921/orm_bitrix24/blob/master/CHANGELOG.md
Requires-Python: >=3.12
Requires-Dist: fast-bitrix24
Requires-Dist: python-dotenv
Requires-Dist: loguru
